docs/source/conf.py
examples/advanced.py
examples/simple.py
faspellchecker/__init__.py
faspellchecker/dictionary.py
faspellchecker/exceptions.py
faspellchecker/fa-dictionary.json.gz
faspellchecker/spellchecker.py
faspellchecker/utils.py
scripts/build_dictionary.py
tests/dictionary_test.py
tests/spellchecker_test.py
tests/utils_test.py
fa_spellchecker-0.3.1.dist-info/LICENSE
fa_spellchecker-0.3.1.dist-info/METADATA
fa_spellchecker-0.3.1.dist-info/WHEEL
fa_spellchecker-0.3.1.dist-info/top_level.txt
fa_spellchecker-0.3.1.dist-info/RECORD
