Metadata-Version: 2.1
Name: fa-spellchecker
Version: 0.3.1
Summary: Pure Python Spell Checking
Author-email: Ashkan Feyzollahi <ashkanfeyzollahi@gmail.com>
License: MIT
Project-URL: homepage, https://github.com/AshkanFeyzollahi/fa-spellchecker
Project-URL: bug-tracker, https://github.com/AshkanFeyzollahi/fa-spellchecker/issues
Project-URL: documentation, https://fa-spellchecker.readthedocs.io/en/latest/
Keywords: python,spelling,natural language processing,nlp,typo,checker,persian
Classifier: Development Status :: 5 - Production/Stable
Classifier: Intended Audience :: Developers
Classifier: Intended Audience :: Information Technology
Classifier: Intended Audience :: Science/Research
Classifier: Topic :: Software Development :: Libraries
Classifier: Topic :: Utilities
Classifier: License :: OSI Approved
Classifier: License :: OSI Approved :: MIT License
Classifier: Programming Language :: Python
Classifier: Programming Language :: Python :: 3
Classifier: Programming Language :: Python :: 3.7
Classifier: Programming Language :: Python :: 3.8
Classifier: Programming Language :: Python :: 3.9
Classifier: Programming Language :: Python :: 3.10
Classifier: Programming Language :: Python :: 3.11
Classifier: Programming Language :: Python :: 3.12
Requires-Python: >=3.7
License-File: LICENSE
Provides-Extra: dev
Requires-Dist: black; extra == "dev"
Requires-Dist: isort; extra == "dev"
